<?xml version = '1.0' encoding = 'UTF-8'?>
<TableProxyOraclev11g class="oracle.dbtools.crest.model.design.storage.oracle.v11g.TableProxyOraclev11g" name="ORDERS" directorySegmentName="seg_0" id="091A05B6-98B5-0833-6D2D-42F2C711481F">
<createdBy>i7C-06</createdBy>
<createdTime>2024-04-05 05:45:48 UTC</createdTime>
<ownerDesignName>4.5</ownerDesignName>
<schemaObject>166B573F-4CB5-CAD7-8E62-863EC19AED53</schemaObject>
<logging>YES</logging>
<partitionedRowMovement>DISABLE</partitionedRowMovement>
<segment>BA1B14CD-6433-8858-681F-204F70CE8A9C</segment>
<tableSpace>BE9C9BF9-00A4-61DF-21C5-E64878221628</tableSpace>
<temporaryChanged>false</temporaryChanged>
<accessDriverType>oracle_loader</accessDriverType>
<rejectLimit></rejectLimit>
<columnProxies itemClass="oracle.dbtools.crest.model.design.storage.oracle.v12c.ColumnProxyOraclev12c">
<ColumnProxy name="ID" id="2CCA5DEE-B8FE-7025-19C9-39874CCB8089">
<createdBy>i7C-06</createdBy>
<createdTime>2024-04-05 05:45:48 UTC</createdTime>
<ownerDesignName>4.5</ownerDesignName>
</ColumnProxy>
<ColumnProxy name="INDATE" id="81D7D99C-6EA8-6D38-3CD0-9D66C6C9E1F6">
<createdBy>i7C-06</createdBy>
<createdTime>2024-04-05 05:45:48 UTC</createdTime>
<ownerDesignName>4.5</ownerDesignName>
</ColumnProxy>
<ColumnProxy name="ORDERNUM" id="B662855D-F17A-7226-F5C3-3ECA7E5E92C3">
<createdBy>i7C-06</createdBy>
<createdTime>2024-04-05 05:45:48 UTC</createdTime>
<ownerDesignName>4.5</ownerDesignName>
</ColumnProxy>
</columnProxies>
<foreignKeys>
<ForeignKey class="oracle.dbtools.crest.model.design.storage.oracle.v10g.FKProxyOraclev10g" name="SYS_C007103" id="347992F3-7051-61FD-4E98-3B4663593EDB">
<createdBy>i7C-06</createdBy>
<createdTime>2024-04-05 05:45:48 UTC</createdTime>
<ownerDesignName>4.5</ownerDesignName>
</ForeignKey>
</foreignKeys>
<primaryKeys>
<PrimaryKey class="oracle.dbtools.crest.model.design.storage.oracle.v10g.PKProxyOraclev10g" name="ORDERS_PK" id="B91EF0C8-9DCF-FF91-B80F-A871C8E2E219">
<createdBy>i7C-06</createdBy>
<createdTime>2024-04-05 05:45:48 UTC</createdTime>
<ownerDesignName>4.5</ownerDesignName>
<schemaObject>166B573F-4CB5-CAD7-8E62-863EC19AED53</schemaObject>
<segment>99C63518-46C0-16AC-8BEE-76448DB8955F</segment>
<tableSpace>BE9C9BF9-00A4-61DF-21C5-E64878221628</tableSpace>
<indexSegment>99C63518-46C0-16AC-8BEE-76448DB8955F</indexSegment>
<indexSort>SORTED</indexSort>
<usingIndex>BY INDEX NAME</usingIndex>
</PrimaryKey>
</primaryKeys>
</TableProxyOraclev11g>